CryptoMax.py
CryptoMax-1.0.0.dist-info/METADATA
CryptoMax-1.0.0.dist-info/WHEEL
CryptoMax-1.0.0.dist-info/top_level.txt
CryptoMax-1.0.0.dist-info/RECORD
