Metadata-Version: 2.1
Name: CryptoMax
Version: 1.0.0
Summary: A Python package for implementing cryptography algorithms
Home-page: https://github.com/shuds13/pyexample
Author: Paul Hudson
Author-email: ehdtvyt@gmail.com
License: BSD 2-clause
Platform: UNKNOWN
Classifier: Development Status :: 1 - Planning
Classifier: Intended Audience :: Science/Research
Classifier: License :: OSI Approved :: BSD License
Classifier: Programming Language :: Python :: 2
Classifier: Programming Language :: Python :: 2.7
Classifier: Programming Language :: Python :: 3
Classifier: Programming Language :: Python :: 3.4
Classifier: Programming Language :: Python :: 3.5
Requires-Dist: numpy
Requires-Dist: sympy
Requires-Dist: pycryptodome
